legend_data_monitor/__init__.py
legend_data_monitor/_version.py
legend_data_monitor/analysis_data.py
legend_data_monitor/core.py
legend_data_monitor/plot_styles.py
legend_data_monitor/plotting.py
legend_data_monitor/run.py
legend_data_monitor/save_data.py
legend_data_monitor/slow_control.py
legend_data_monitor/string_visualization.py
legend_data_monitor/subsystem.py
legend_data_monitor/utils.py
legend_data_monitor/config/p03_L200_phy_r000.yaml
legend_data_monitor/config/p03_r000_L200_hdf_example.yaml
legend_data_monitor/config/slow_control_example.yaml
legend_data_monitor/settings/SC-params.yaml
legend_data_monitor/settings/flags.yaml
legend_data_monitor/settings/ignore-keys.yaml
legend_data_monitor/settings/no-pulser-dets.yaml
legend_data_monitor/settings/par-settings.yaml
legend_data_monitor/settings/parameter-tiers.yaml
legend_data_monitor/settings/remove-dets.yaml
legend_data_monitor/settings/remove-keys-COAXp04.yaml
legend_data_monitor/settings/remove-keys.yaml
legend_data_monitor/settings/special-parameters.yaml
legend_data_monitor-2.1.3.dist-info/licenses/LICENSE
legend_data_monitor-2.1.3.dist-info/METADATA
legend_data_monitor-2.1.3.dist-info/WHEEL
legend_data_monitor-2.1.3.dist-info/entry_points.txt
legend_data_monitor-2.1.3.dist-info/top_level.txt
legend_data_monitor-2.1.3.dist-info/RECORD
