Metadata-Version: 2.4
Name: legend-data-monitor
Version: 2.1.3
Summary: Python package for LEGEND data monitoring
Author-email: Sofia Calgaro <sofia.calgaro@physik.uzh.ch>, Michele Morella <michele.morella@gssi.it>
Maintainer: The LEGEND Collaboration
License: MIT
Keywords: LEGEND,monitoring,physics,data-analysis
Classifier: Development Status :: 4 - Beta
Classifier: Intended Audience :: Developers
Classifier: Intended Audience :: Science/Research
Classifier: Operating System :: MacOS
Classifier: Operating System :: POSIX
Classifier: Operating System :: Unix
Classifier: Programming Language :: Python
Classifier: Programming Language :: Python :: 3
Classifier: Topic :: Scientific/Engineering
Classifier: Topic :: Scientific/Engineering :: Information Analysis
Classifier: Topic :: Scientific/Engineering :: Mathematics
Classifier: Topic :: Scientific/Engineering :: Physics
Classifier: Topic :: Software Development
Requires-Python: >=3.9
License-File: LICENSE
Requires-Dist: pygama
Requires-Dist: pylegendmeta>=0.9
Requires-Dist: seaborn
Provides-Extra: all
Requires-Dist: legend-data-monitor[docs,test]; extra == "all"
Provides-Extra: docs
Requires-Dist: furo; extra == "docs"
Requires-Dist: myst-parser; extra == "docs"
Requires-Dist: sphinx; extra == "docs"
Requires-Dist: sphinx-copybutton; extra == "docs"
Provides-Extra: test
Requires-Dist: pre-commit; extra == "test"
Requires-Dist: pytest>=6.0; extra == "test"
Requires-Dist: pytest-cov; extra == "test"
Requires-Dist: freezegun==1.5.5; extra == "test"
Dynamic: license-file
